core/__init__.py
core/data.py
core/download.py
core/files.py
core/gui.py
core/telegram.py
core/web.py
PyZest-0.1.0.dist-info/METADATA
PyZest-0.1.0.dist-info/WHEEL
PyZest-0.1.0.dist-info/top_level.txt
PyZest-0.1.0.dist-info/RECORD
