Metadata-Version: 2.1
Name: PyZest
Version: 0.1.0
Summary: Easy Python Tools
Home-page: https://github.com/redflymeer/PyZest
Author: RedFlyMeer
Author-email: redflymeer@gmail.com
Keywords: python easy http gui telegram web files
Classifier: Programming Language :: Python :: 3
Classifier: License :: OSI Approved :: MIT License
Requires-Python: >=3.6
Requires-Dist: requests>=2.25.1
Requires-Dist: beautifulsoup4>=4.9.3
Requires-Dist: aiogram>=2.23.1
Requires-Dist: tqdm>=4.60.0
Requires-Dist: PySide6>=6.4.0
